Metadata-Version: 2.1
Name: db-legends-api
Version: 1.83.4
Summary: Python module to retrieve DB Legends character information
Author: ohioman02
Author-email: gdnunuuwu@gmail.com
License-File: LICENSE
